{
    "ambientocclusion": false,
    "textures": {
        "particle": "block/iron_bars",
        "bars": "block/iron_bars"
    },
    "elements": [
        {   "from": [ 7, 7, 14 ],
            "to": [ 9, 9, 16 ],
            "faces": {
                "west":  { "uv": [ 14, 7,  16, 9 ], "texture": "#bars" },
                "east":  { "uv": [ 14, 7,  16, 9 ], "texture": "#bars" },
                "south": { "uv": [ 14, 7,  16, 9 ], "texture": "#bars" },
                "up":    { "uv": [ 14, 7,  16, 9 ], "texture": "#bars" },
                "down":  { "uv": [ 14, 7,  16, 9 ], "texture": "#bars" }
            }
        },
        {   "from": [ 7, 0, 12 ],
            "to": [ 9, 16, 14 ],
            "faces": {
                "west":  { "uv": [ 12, 0,  14, 16 ], "texture": "#bars" },
                "east":  { "uv": [ 12, 0,  14, 16 ], "texture": "#bars" },
                "north": { "uv": [ 12, 0,  14, 16 ], "texture": "#bars" },
                "south": { "uv": [ 12, 0,  14, 16 ], "texture": "#bars" },
                "up":    { "uv": [ 12, 0,  14, 2 ], "texture": "#bars" },
                "down":  { "uv": [ 12, 14,  14, 16 ], "texture": "#bars" }
            }
        },
        {   "from": [ 7, 2, 9 ],
            "to": [ 9, 4, 12 ],
            "faces": {
                "west":  { "uv": [ 9, 12,  12, 14 ], "texture": "#bars" },
                "east":  { "uv": [ 9, 12,  12, 14 ], "texture": "#bars" },
                "up":    { "uv": [ 9, 12,  12, 14 ], "texture": "#bars", "rotation": 90},
                "down":  { "uv": [ 9, 12,  12, 14 ], "texture": "#bars", "rotation": 270}
            }
        }
    ]
}

